swarmauri_tests_griffe/__init__.py
swarmauri_tests_griffe-0.1.1.dev1.dist-info/METADATA
swarmauri_tests_griffe-0.1.1.dev1.dist-info/WHEEL
swarmauri_tests_griffe-0.1.1.dev1.dist-info/entry_points.txt
swarmauri_tests_griffe-0.1.1.dev1.dist-info/licenses/LICENSE
swarmauri_tests_griffe-0.1.1.dev1.dist-info/RECORD
