Metadata-Version: 2.4
Name: swarmauri_tests_griffe
Version: 0.1.1.dev1
Summary: Pytest plugin that turns Griffe inspection warnings into failing quality gates for Swarmauri packages.
License: Apache-2.0
License-File: LICENSE
Keywords: swarmauri,pytest,griffe,static analysis,developer experience,quality gates
Author: Jacob Stewart
Author-email: jacob@swarmauri.com
Requires-Python: >=3.10
Classifier: Development Status :: 1 - Planning
Classifier: Framework :: Pytest
Classifier: Intended Audience :: Developers
Classifier: Topic :: Software Development :: Quality Assurance
Classifier: Programming Language :: Python :: 3
Classifier: Programming Language :: Python :: 3.10
Classifier: Programming Language :: Python :: 3.11
Classifier: Programming Language :: Python :: 3.12
Requires-Dist: griffe (>=0.48)
Requires-Dist: pytest (>=8.0)
Requires-Dist: tomli ; python_version < "3.11"
